wellwiz/__init__.py
wellwiz/common.py
wellwiz/folium.py
wellwiz/wellwiz.py
wellwiz-0.0.3.dist-info/LICENSE
wellwiz-0.0.3.dist-info/METADATA
wellwiz-0.0.3.dist-info/WHEEL
wellwiz-0.0.3.dist-info/entry_points.txt
wellwiz-0.0.3.dist-info/top_level.txt
wellwiz-0.0.3.dist-info/RECORD
