Metadata-Version: 2.1
Name: wellwiz
Version: 0.0.3
Summary: A developing python package to gather information about the gas and oil wells and know the risk through a map visualization.
Author-email: Shabiha Hossain <sabihahossain4105@gmail.com>
License: MIT License
Project-URL: Homepage, https://github.com/OmiimO05/wellwiz
Keywords: wellwiz
Classifier: Intended Audience :: Developers
Classifier: License :: OSI Approved :: MIT License
Classifier: Natural Language :: English
Classifier: Programming Language :: Python :: 3.8
Classifier: Programming Language :: Python :: 3.9
Classifier: Programming Language :: Python :: 3.10
Classifier: Programming Language :: Python :: 3.11
Classifier: Programming Language :: Python :: 3.12
Requires-Python: >=3.8
License-File: LICENSE
Requires-Dist: numpy
Requires-Dist: ipyleaflet
Requires-Dist: folium
Requires-Dist: pandas
Requires-Dist: pyshp
Requires-Dist: geopandas
Requires-Dist: localtileserver
Requires-Dist: pylance
Requires-Dist: panel
Requires-Dist: geopy
Requires-Dist: rasterio
Requires-Dist: scipy
Requires-Dist: shapely
Requires-Dist: pyproj
Requires-Dist: SQLAlchemy
Requires-Dist: bokeh
Requires-Dist: poetry
Provides-Extra: all
Requires-Dist: wellwiz[extra] ; extra == 'all'
Provides-Extra: extra
Requires-Dist: pandas ; extra == 'extra'
